oasis/__init__.py
oasis/clock/__init__.py
oasis/clock/clock.py
oasis/inference/__init__.py
oasis/inference/inference_manager.py
oasis/inference/inference_thread.py
oasis/social_agent/__init__.py
oasis/social_agent/agent.py
oasis/social_agent/agent_action.py
oasis/social_agent/agent_environment.py
oasis/social_agent/agent_graph.py
oasis/social_agent/agents_generator.py
oasis/social_platform/__init__.py
oasis/social_platform/channel.py
oasis/social_platform/config/__init__.py
oasis/social_platform/config/neo4j.py
oasis/social_platform/config/user.py
oasis/social_platform/database.py
oasis/social_platform/platform.py
oasis/social_platform/platform_utils.py
oasis/social_platform/process_recsys_posts.py
oasis/social_platform/recsys.py
oasis/social_platform/schema/comment.sql
oasis/social_platform/schema/comment_dislike.sql
oasis/social_platform/schema/comment_like.sql
oasis/social_platform/schema/dislike.sql
oasis/social_platform/schema/follow.sql
oasis/social_platform/schema/like.sql
oasis/social_platform/schema/mute.sql
oasis/social_platform/schema/post.sql
oasis/social_platform/schema/product.sql
oasis/social_platform/schema/rec.sql
oasis/social_platform/schema/trace.sql
oasis/social_platform/schema/user.sql
oasis/social_platform/typing.py
oasis/testing/__init__.py
oasis/testing/show_db.py
oasis_ai-0.0.1.dist-info/LICENSE
oasis_ai-0.0.1.dist-info/LICENSES/license_template.txt
oasis_ai-0.0.1.dist-info/LICENSES/update_license.py
oasis_ai-0.0.1.dist-info/METADATA
oasis_ai-0.0.1.dist-info/WHEEL
oasis_ai-0.0.1.dist-info/RECORD
