Metadata-Version: 2.1
Name: oasis-ai
Version: 0.0.1
Summary: Open Agents Social Interaction Simulations on a Large Scale
Home-page: https://github.com/camel-ai/oasis.git
License: Apache-2.0
Keywords: LLM,agent,social-network,graph,recommendation-system,communicative-ai,ai-societies,artificial-intelligence,deep-learning,multi-agent-systems,cooperative-ai,natural-language-processing,large-language-models
Author: CAMEL-AI.org
Requires-Python: >=3.10.0,<3.12
Classifier: License :: OSI Approved :: Apache Software License
Classifier: Programming Language :: Python :: 3
Classifier: Programming Language :: Python :: 3.10
Classifier: Programming Language :: Python :: 3.11
Requires-Dist: cairocffi (==1.7.1)
Requires-Dist: camel-ai (==0.2.2)
Requires-Dist: igraph (==0.11.6)
Requires-Dist: neo4j (==5.23.0)
Requires-Dist: openapi-spec-validator (==0.7.1)
Requires-Dist: pandas (==2.2.2)
Requires-Dist: pillow (==10.3.0)
Requires-Dist: prance (==23.6.21.0)
Requires-Dist: pre-commit (==3.7.1)
Requires-Dist: pytest (==8.2.0)
Requires-Dist: pytest-asyncio (==0.23.6)
Requires-Dist: sentence-transformers (==3.0.0)
Requires-Dist: slack_sdk (==3.31.0)
Requires-Dist: unstructured (==0.13.7)
Project-URL: Repository, https://github.com/camel-ai/oasis.git
